avito/__init__.py
avito_py-0.0.1.1.dist-info/LICENSE
avito_py-0.0.1.1.dist-info/METADATA
avito_py-0.0.1.1.dist-info/WHEEL
avito_py-0.0.1.1.dist-info/RECORD
